.gitattributes
.gitignore
LICENSE
README.md
env.yaml
image.png
setup.py
src/BCscannerBWA/__init__.py
src/BCscannerBWA/add_umi.py
src/BCscannerBWA/bamGetumi.py
src/BCscannerBWA/barcodeRef.py
src/BCscannerBWA/fastq2sam.py
src/BCscannerBWA/getBarcodeSeqence.py
src/BCscannerBWA/sam2fq.py
src/BCscannerBWA.egg-info/PKG-INFO
src/BCscannerBWA.egg-info/SOURCES.txt
src/BCscannerBWA.egg-info/dependency_links.txt
src/BCscannerBWA.egg-info/top_level.txt