Metadata-Version: 2.1
Name: BCscannerBWA
Version: 1.0.0
Summary: Barcode split for Cyclone
Home-page: https://github.com/dawangran/BCscannerBWA
Author: Dawn
Author-email: 605547565@qq.com
Classifier: Programming Language :: Python :: 3
Classifier: License :: OSI Approved :: MIT License
Classifier: Operating System :: OS Independent
Requires-Python: >=3.8
License-File: LICENSE
